Game_generation_utils/__init__.py
Game_generation_utils/generator.py
Game_generation_utils-0.8.dist-info/LICENSE
Game_generation_utils-0.8.dist-info/METADATA
Game_generation_utils-0.8.dist-info/WHEEL
Game_generation_utils-0.8.dist-info/top_level.txt
Game_generation_utils-0.8.dist-info/RECORD
