Metadata-Version: 2.1
Name: Game_generation_utils
Version: 0.8
Summary: A 2D terrain generation utility
Home-page: https://github.com/LuisMiguelTrinidad/2d-terrain-Gen
Author: Luis Miguel Trinidad Salvador
Author-email: your.email@example.com
Classifier: Programming Language :: Python :: 3
Classifier: Operating System :: OS Independent
Requires-Python: >=3.6
License-File: LICENSE
Requires-Dist: opensimplex
Requires-Dist: numpy
Requires-Dist: matplotlib
Requires-Dist: plotly
Requires-Dist: pandas
Requires-Dist: nbformat
